[
	{
		"ISBN": "978-4-287-21477-2",
		"Author": "Cote, Freya G.",
		"Publisher": "JW Wiley",
		"Title": "dui",
		"ReleaseDate": "2016-11-11T23:19:32-08:00"
	},
	{
		"ISBN": "978-3-523-12766-9",
		"Author": "Scott, Naomi T.",
		"Publisher": "O'Reilly ",
		"Title": "consectetuer",
		"ReleaseDate": "2016-07-26T08:26:05-07:00"
	},
	{
		"ISBN": "978-3-141-51885-9",
		"Author": "Miranda, Aaron F.",
		"Publisher": "Prentice Hall",
		"Title": "Duis elementum",
		"ReleaseDate": "2015-11-14T21:16:48-08:00"
	},
	{
		"ISBN": "978-7-998-18228-3",
		"Author": "Thornton, Sara O.",
		"Publisher": "O'Reilly ",
		"Title": "Curabitur vel",
		"ReleaseDate": "2015-07-03T16:10:39-07:00"
	},
	{
		"ISBN": "978-8-473-69261-2",
		"Author": "West, Jamalia T.",
		"Publisher": "O'Reilly ",
		"Title": "Nullam",
		"ReleaseDate": "2016-02-15T23:38:30-08:00"
	},
	{
		"ISBN": "978-4-396-95439-1",
		"Author": "Larson, Ella C.",
		"Publisher": "JW Wiley",
		"Title": "purus ac",
		"ReleaseDate": "2015-07-29T02:19:01-07:00"
	},
	{
		"ISBN": "978-6-495-51375-9",
		"Author": "Leach, Inga M.",
		"Publisher": "Addison Wesley",
		"Title": "Aenean",
		"ReleaseDate": "2015-02-18T17:19:47-08:00"
	},
	{
		"ISBN": "978-8-635-36519-1",
		"Author": "Wilson, Candice V.",
		"Publisher": "JW Wiley",
		"Title": "risus In",
		"ReleaseDate": "2015-04-28T09:42:02-07:00"
	},
	{
		"ISBN": "978-1-366-25321-7",
		"Author": "Briggs, Angelica M.",
		"Publisher": "JW Wiley",
		"Title": "Sed diam lorem",
		"ReleaseDate": "2015-05-01T08:40:02-07:00"
	},
	{
		"ISBN": "978-7-893-62364-5",
		"Author": "Harris, Prescott T.",
		"Publisher": "O'Reilly ",
		"Title": "Aliquam erat volutpat",
		"ReleaseDate": "2016-01-06T20:14:28-08:00"
	},
	{
		"ISBN": "978-6-924-85632-4",
		"Author": "Burch, Tashya N.",
		"Publisher": "O'Reilly ",
		"Title": "ac",
		"ReleaseDate": "2015-06-17T23:53:43-07:00"
	},
	{
		"ISBN": "978-6-124-97393-9",
		"Author": "Boyle, Fuller Y.",
		"Publisher": "Prentice Hall",
		"Title": "egestas a scelerisque",
		"ReleaseDate": "2015-09-09T21:22:02-07:00"
	},
	{
		"ISBN": "978-2-152-63238-8",
		"Author": "Duncan, Jarrod Z.",
		"Publisher": "Addison Wesley",
		"Title": "dignissim tempor",
		"ReleaseDate": "2014-12-29T02:41:51-08:00"
	},
	{
		"ISBN": "978-7-376-53424-9",
		"Author": "Sweet, Sasha Y.",
		"Publisher": "JW Wiley",
		"Title": "ipsum Phasellus",
		"ReleaseDate": "2015-12-09T11:25:15-08:00"
	},
	{
		"ISBN": "978-7-842-11395-5",
		"Author": "Oconnor, Hadassah Q.",
		"Publisher": "JW Wiley",
		"Title": "orci adipiscing non,",
		"ReleaseDate": "2015-04-24T01:06:15-07:00"
	},
	{
		"ISBN": "978-6-228-24459-6",
		"Author": "Rojas, Wing O.",
		"Publisher": "Addison Wesley",
		"Title": "natoque penatibus",
		"ReleaseDate": "2015-08-12T20:59:43-07:00"
	},
	{
		"ISBN": "978-3-179-96728-9",
		"Author": "Blackburn, Kim B.",
		"Publisher": "O'Reilly ",
		"Title": "rutrum justo.",
		"ReleaseDate": "2015-05-19T04:55:37-07:00"
	},
	{
		"ISBN": "978-1-879-55568-3",
		"Author": "Peterson, Lillith H.",
		"Publisher": "Prentice Hall",
		"Title": "penatibus",
		"ReleaseDate": "2016-10-03T09:04:28-07:00"
	},
	{
		"ISBN": "978-4-415-97258-7",
		"Author": "Cabrera, Madonna U.",
		"Publisher": "O'Reilly ",
		"Title": "Nunc quis arcu",
		"ReleaseDate": "2014-12-29T05:35:39-08:00"
	},
	{
		"ISBN": "978-8-359-93821-2",
		"Author": "Armstrong, Olga T.",
		"Publisher": "Prentice Hall",
		"Title": "dapibus ligula",
		"ReleaseDate": "2015-12-08T13:13:04-08:00"
	},
	{
		"ISBN": "978-6-937-21222-5",
		"Author": "Whitehead, Sophia C.",
		"Publisher": "Prentice Hall",
		"Title": "urna",
		"ReleaseDate": "2016-10-12T21:10:16-07:00"
	},
	{
		"ISBN": "978-6-477-18656-2",
		"Author": "Langley, Eden C.",
		"Publisher": "Addison Wesley",
		"Title": "enim",
		"ReleaseDate": "2016-08-16T12:49:17-07:00"
	},
	{
		"ISBN": "978-9-783-58562-1",
		"Author": "Keith, Thaddeus I.",
		"Publisher": "JW Wiley",
		"Title": "ligula elit pretium",
		"ReleaseDate": "2016-03-14T22:46:01-07:00"
	},
	{
		"ISBN": "978-7-815-19928-4",
		"Author": "Wilkins, Simon E.",
		"Publisher": "JW Wiley",
		"Title": "Nulla",
		"ReleaseDate": "2015-09-30T21:07:17-07:00"
	},
	{
		"ISBN": "978-9-224-76556-8",
		"Author": "Roth, Raphael N.",
		"Publisher": "Prentice Hall",
		"Title": "dictum magna",
		"ReleaseDate": "2016-01-07T06:37:13-08:00"
	},
	{
		"ISBN": "978-4-354-96788-1",
		"Author": "Kirk, Tana O.",
		"Publisher": "Addison Wesley",
		"Title": "aliquam",
		"ReleaseDate": "2016-10-11T17:29:17-07:00"
	},
	{
		"ISBN": "978-6-169-41923-2",
		"Author": "Velez, Anika I.",
		"Publisher": "O'Reilly ",
		"Title": "arcu. Sed",
		"ReleaseDate": "2015-07-05T08:16:10-07:00"
	},
	{
		"ISBN": "978-1-727-94563-2",
		"Author": "Wilcox, Caldwell G.",
		"Publisher": "O'Reilly ",
		"Title": "ante. Nunc",
		"ReleaseDate": "2015-12-22T19:58:23-08:00"
	},
	{
		"ISBN": "978-5-861-72347-8",
		"Author": "Morgan, Guy V.",
		"Publisher": "Addison Wesley",
		"Title": "et arcu imperdiet",
		"ReleaseDate": "2015-08-29T12:28:53-07:00"
	},
	{
		"ISBN": "978-8-197-81135-7",
		"Author": "Merritt, Kylynn F.",
		"Publisher": "Addison Wesley",
		"Title": "consequat purus.",
		"ReleaseDate": "2015-07-18T22:13:26-07:00"
	},
	{
		"ISBN": "978-1-679-24329-7",
		"Author": "Harrison, Zephr E.",
		"Publisher": "JW Wiley",
		"Title": "sagittis semper. Nam",
		"ReleaseDate": "2016-09-21T12:20:24-07:00"
	},
	{
		"ISBN": "978-6-588-78215-7",
		"Author": "Reed, Merrill G.",
		"Publisher": "Prentice Hall",
		"Title": "mauris",
		"ReleaseDate": "2016-07-26T06:01:53-07:00"
	},
	{
		"ISBN": "978-8-375-45683-1",
		"Author": "Robertson, Jameson X.",
		"Publisher": "Addison Wesley",
		"Title": "viverra.",
		"ReleaseDate": "2015-03-16T16:56:03-07:00"
	},
	{
		"ISBN": "978-8-472-11533-7",
		"Author": "Adkins, Larissa D.",
		"Publisher": "Prentice Hall",
		"Title": "eget,",
		"ReleaseDate": "2016-02-06T08:32:32-08:00"
	},
	{
		"ISBN": "978-5-522-76718-1",
		"Author": "Douglas, Tucker A.",
		"Publisher": "JW Wiley",
		"Title": "pharetra nibh.",
		"ReleaseDate": "2016-10-05T04:14:54-07:00"
	},
	{
		"ISBN": "978-6-973-47995-7",
		"Author": "Monroe, Imelda B.",
		"Publisher": "Prentice Hall",
		"Title": "magna.",
		"ReleaseDate": "2016-04-30T03:21:20-07:00"
	},
	{
		"ISBN": "978-1-696-68515-6",
		"Author": "Cruz, Odysseus E.",
		"Publisher": "O'Reilly ",
		"Title": "lectus, a",
		"ReleaseDate": "2016-05-21T06:56:27-07:00"
	},
	{
		"ISBN": "978-4-381-61223-7",
		"Author": "Casey, Alden A.",
		"Publisher": "Addison Wesley",
		"Title": "nibh. Aliquam",
		"ReleaseDate": "2015-10-04T22:51:33-07:00"
	},
	{
		"ISBN": "978-9-943-59843-2",
		"Author": "Rocha, Phelan F.",
		"Publisher": "JW Wiley",
		"Title": "urna. Nullam",
		"ReleaseDate": "2015-10-06T18:37:35-07:00"
	},
	{
		"ISBN": "978-9-888-13691-6",
		"Author": "Austin, Jared G.",
		"Publisher": "Addison Wesley",
		"Title": "eros.",
		"ReleaseDate": "2016-10-23T01:59:47-07:00"
	},
	{
		"ISBN": "978-9-575-99576-6",
		"Author": "Jensen, Danielle E.",
		"Publisher": "Prentice Hall",
		"Title": "mi fringilla mi",
		"ReleaseDate": "2016-08-15T11:22:03-07:00"
	},
	{
		"ISBN": "978-8-266-15747-7",
		"Author": "William, Daria L.",
		"Publisher": "Addison Wesley",
		"Title": "luctus",
		"ReleaseDate": "2014-12-08T18:05:41-08:00"
	},
	{
		"ISBN": "978-8-757-56935-3",
		"Author": "Rollins, Ima D.",
		"Publisher": "Addison Wesley",
		"Title": "nulla magna,",
		"ReleaseDate": "2016-10-23T12:59:22-07:00"
	},
	{
		"ISBN": "978-9-745-64471-4",
		"Author": "Howe, Tobias R.",
		"Publisher": "Addison Wesley",
		"Title": "rutrum, justo. Praesent",
		"ReleaseDate": "2016-07-01T07:07:33-07:00"
	},
	{
		"ISBN": "978-9-693-44757-6",
		"Author": "Trevino, Orlando Q.",
		"Publisher": "Addison Wesley",
		"Title": "nunc",
		"ReleaseDate": "2016-07-19T01:01:28-07:00"
	},
	{
		"ISBN": "978-6-724-99517-2",
		"Author": "Whitney, Finn P.",
		"Publisher": "Addison Wesley",
		"Title": "Cras vehicula aliquet",
		"ReleaseDate": "2015-03-28T11:19:52-07:00"
	},
	{
		"ISBN": "978-4-721-76883-9",
		"Author": "Vincent, Jade V.",
		"Publisher": "Addison Wesley",
		"Title": "sociis natoque",
		"ReleaseDate": "2015-02-10T18:24:35-08:00"
	},
	{
		"ISBN": "978-6-819-72692-8",
		"Author": "Bennett, Urielle P.",
		"Publisher": "O'Reilly ",
		"Title": "aliquet",
		"ReleaseDate": "2016-10-27T02:35:36-07:00"
	},
	{
		"ISBN": "978-6-791-49435-9",
		"Author": "Hensley, Christen G.",
		"Publisher": "JW Wiley",
		"Title": "sed dictum",
		"ReleaseDate": "2016-03-16T23:59:49-07:00"
	},
	{
		"ISBN": "978-6-331-46279-1",
		"Author": "Mercer, Violet H.",
		"Publisher": "JW Wiley",
		"Title": "consectetuer",
		"ReleaseDate": "2016-06-06T06:36:53-07:00"
	},
	{
		"ISBN": "978-9-994-25742-4",
		"Author": "Merritt, Winifred I.",
		"Publisher": "JW Wiley",
		"Title": "ullamcorper",
		"ReleaseDate": "2015-12-25T01:27:53-08:00"
	},
		{
		"ISBN": "978-7-512-18872-9",
		"Author": "William, Colby M.",
		"Publisher": "O'Reilly ",
		"Title": "amet",
		"ReleaseDate": "2015-11-20T11:27:15-08:00"
	},
	{
		"ISBN": "978-7-573-57983-7",
		"Author": "Mcintosh, Connor N.",
		"Publisher": "Addison Wesley",
		"Title": "primis in",
		"ReleaseDate": "2016-03-13T08:08:03-07:00"
	},
	{
		"ISBN": "978-7-116-14349-5",
		"Author": "Stanton, Amal K.",
		"Publisher": "Addison Wesley",
		"Title": "Nunc mauris",
		"ReleaseDate": "2015-06-26T11:49:21-07:00"
	},
	{
		"ISBN": "978-3-639-35343-4",
		"Author": "Vinson, Rachel T.",
		"Publisher": "Prentice Hall",
		"Title": "eget laoreet posuere",
		"ReleaseDate": "2015-11-10T19:56:12-08:00"
	},
	{
		"ISBN": "978-2-442-99242-9",
		"Author": "Robbins, Mariam J.",
		"Publisher": "O'Reilly ",
		"Title": "elit",
		"ReleaseDate": "2015-06-19T23:09:33-07:00"
	},
	{
		"ISBN": "978-8-488-63658-2",
		"Author": "Wells, Ava E.",
		"Publisher": "O'Reilly ",
		"Title": "id magna et",
		"ReleaseDate": "2015-02-18T18:40:47-08:00"
	},
	{
		"ISBN": "978-3-657-18162-4",
		"Author": "Wallace, Chase N.",
		"Publisher": "Prentice Hall",
		"Title": "netus et",
		"ReleaseDate": "2016-04-10T05:38:58-07:00"
	},
	{
		"ISBN": "978-7-681-79845-8",
		"Author": "English, Boris R.",
		"Publisher": "Prentice Hall",
		"Title": "Nam porttitor scelerisque",
		"ReleaseDate": "2016-05-13T07:47:48-07:00"
	},
	{
		"ISBN": "978-6-871-74997-9",
		"Author": "Schmidt, Lenore E.",
		"Publisher": "Prentice Hall",
		"Title": "Quisque",
		"ReleaseDate": "2015-02-16T04:06:59-08:00"
	},
	{
		"ISBN": "978-2-527-98248-7",
		"Author": "Hensley, Hayley T.",
		"Publisher": "JW Wiley",
		"Title": "non vestibulum nec,",
		"ReleaseDate": "2016-01-12T07:09:16-08:00"
	},
	{
		"ISBN": "978-2-884-65575-7",
		"Author": "Gilbert, Caesar N.",
		"Publisher": "Prentice Hall",
		"Title": "ante Nunc mauris",
		"ReleaseDate": "2015-07-06T10:40:49-07:00"
	},
	{
		"ISBN": "978-2-181-29269-2",
		"Author": "Koch, Arthur F.",
		"Publisher": "Addison Wesley",
		"Title": "felis",
		"ReleaseDate": "2015-08-30T13:29:51-07:00"
	},
	{
		"ISBN": "978-5-764-21736-4",
		"Author": "Lamb, Amethyst R.",
		"Publisher": "Prentice Hall",
		"Title": "ultrices posuere cubilia",
		"ReleaseDate": "2015-11-20T16:53:55-08:00"
	},
	{
		"ISBN": "978-6-615-54921-4",
		"Author": "Petty, Otto L.",
		"Publisher": "Prentice Hall",
		"Title": "enim",
		"ReleaseDate": "2015-03-23T07:52:52-07:00"
	},
	{
		"ISBN": "978-6-646-26929-1",
		"Author": "Rodriquez, John O.",
		"Publisher": "Addison Wesley",
		"Title": "ornare sagittis felis",
		"ReleaseDate": "2016-05-21T21:13:09-07:00"
	},
	{
		"ISBN": "978-8-577-38388-1",
		"Author": "Curry, Cecilia S.",
		"Publisher": "Addison Wesley",
		"Title": "pede",
		"ReleaseDate": "2016-04-27T01:31:20-07:00"
	},
	{
		"ISBN": "978-1-234-33276-9",
		"Author": "Mullen, Leslie L.",
		"Publisher": "JW Wiley",
		"Title": "mi lorem",
		"ReleaseDate": "2016-08-13T12:17:20-07:00"
	},
	{
		"ISBN": "978-1-992-49694-7",
		"Author": "Brennan, Destiny T.",
		"Publisher": "JW Wiley",
		"Title": "quam",
		"ReleaseDate": "2016-05-27T02:58:53-07:00"
	},
	{
		"ISBN": "978-1-776-73473-5",
		"Author": "Wilkins, Hiroko S.",
		"Publisher": "O'Reilly ",
		"Title": "laoreet lectus quis",
		"ReleaseDate": "2015-01-17T12:59:16-08:00"
	},
	{
		"ISBN": "978-9-122-56111-1",
		"Author": "Koch, Griffin R.",
		"Publisher": "JW Wiley",
		"Title": "Cume”,
		"ReleaseDate": "2016-09-27T09:21:30-07:00"
	},
	{
		"ISBN": "978-2-695-25133-9",
		"Author": "Ratliff, Yoko S.",
		"Publisher": "O'Reilly ",
		"Title": "metus facilisis",
		"ReleaseDate": "2016-04-12T01:58:03-07:00"
	},
	{
		"ISBN": "978-4-561-23854-9",
		"Author": "Dillon, Rosalyn Y.",
		"Publisher": "O'Reilly ",
		"Title": "arcu et",
		"ReleaseDate": "2015-07-12T05:49:22-07:00"
	},
	{
		"ISBN": "978-8-699-73422-3",
		"Author": "Grimes, Guy V.",
		"Publisher": "O'Reilly ",
		"Title": "scelerisque",
		"ReleaseDate": "2016-09-25T12:53:22-07:00"
	}
]